cogeol-0.1.5.dist-info/METADATA
cogeol-0.1.5.dist-info/WHEEL
cogeol-0.1.5.dist-info/entry_points.txt
cogeol/__init__.py
cogeol/_versions.py
cogeol/error.py
cogeol/py.typed
cogeol/py.typed.license
cogeol-0.1.5.dist-info/RECORD
