Metadata-Version: 2.4
Name: cogeol
Version: 0.1.5
Summary: Align with supported Python versions - automated with endoflife.date
Author: open-nudge
Maintainer: open-nudge
License-Expression: Apache-2.0
Classifier: Development Status :: 2 - Pre-Alpha
Classifier: Intended Audience :: Developers
Classifier: Programming Language :: Python
Classifier: Programming Language :: Python :: 3 :: Only
Classifier: Programming Language :: Python :: 3.11
Classifier: Programming Language :: Python :: 3.12
Classifier: Programming Language :: Python :: 3.13
Classifier: Topic :: Software Development :: Libraries
Classifier: Topic :: Software Development :: Libraries :: Python Modules
Classifier: Topic :: Internet
Classifier: Topic :: Scientific/Engineering
Classifier: Topic :: Security
Classifier: Topic :: Utilities
Classifier: Typing :: Typed
Project-URL: Changelog, https://github.com/open-nudge/cogeol/blob/master/CHANGELOG.md
Project-URL: Documentation, https://open-nudge.github.io/cogeol
Project-URL: Homepage, https://open-nudge.github.io/cogeol
Project-URL: Issues, https://github.com/open-nudge/cogeol/issues
Project-URL: Repository, https://github.com/open-nudge/cogeol
Requires-Python: >=3.11
Requires-Dist: cogapp>=3.5.0
